expylain/__init__.py
expylain-0.0.1.dist-info/DESCRIPTION.rst
expylain-0.0.1.dist-info/METADATA
expylain-0.0.1.dist-info/RECORD
expylain-0.0.1.dist-info/WHEEL
expylain-0.0.1.dist-info/metadata.json
expylain-0.0.1.dist-info/top_level.txt
