Metadata-Version: 2.0
Name: expylain
Version: 0.0.1
Summary: 
Home-page: https://github.com/SamLau95/expylain
Author: Sam Lau
Author-email: samlau95@gmail.com
License: BSD 3-Clause
Keywords: jupyter expylain visualization random
Platform: UNKNOWN
Classifier: Development Status :: 3 - Alpha
Classifier: Intended Audience :: Developers
Classifier: Topic :: Software Development :: Build Tools
Classifier: Programming Language :: Python :: 3
Classifier: Programming Language :: Python :: 3.3
Classifier: Programming Language :: Python :: 3.4
Classifier: Programming Language :: Python :: 3.5
Classifier: Framework :: Jupyter
Provides-Extra: dev
Requires-Dist: check-manifest; extra == 'dev'
Provides-Extra: test
Requires-Dist: coverage; extra == 'test'
